twitterer/__init__.py
twitterer/authenticator.py
twitterer/collector.py
twitterer/const.py
twitterer/customsoup.py
twitterer/py.typed
twitterer/scraping_progress.py
twitterer/tweet.py
twitterer/twitterer.py
twitterer-0.3.1.dist-info/LICENSE
twitterer-0.3.1.dist-info/METADATA
twitterer-0.3.1.dist-info/WHEEL
twitterer-0.3.1.dist-info/top_level.txt
twitterer-0.3.1.dist-info/RECORD
