Metadata-Version: 2.1
Name: twitterer
Version: 0.3.1
Summary: Python's package to scrape Twitter with selenium.
License: MIT License
Project-URL: Homepage, https://github.com/CatBraaain/twitterer
Keywords: twitter,selenium,scrape,scraping,scraper,twitterer,bot
License-File: LICENSE
Requires-Dist: bs4
Requires-Dist: fake-useragent
Requires-Dist: jsonpickle
Requires-Dist: lxml
Requires-Dist: python-dotenv
Requires-Dist: selenium >=4.6
Requires-Dist: types-beautifulsoup4
Requires-Dist: rich
